cgroup_parser/__init__.py
cgroup_parser/utils.py
cgroup_parser/cgroups/__init__.py
cgroup_parser/cgroups/cgroup.py
cgroup_parser/cgroups/cgroups.py
cgroup_parser/cgroups/mountpoint.py
cgroup_parser/cgroups/subsys.py
cgroup_parser/runtime/__init__.py
cgroup_parser/runtime/quota_linux.py
cgroup_parser/runtime/quota_unsupported.py
cgroup_parser/runtime/runtime.py
cgroup_parser-0.0.2.dist-info/METADATA
cgroup_parser-0.0.2.dist-info/RECORD
cgroup_parser-0.0.2.dist-info/WHEEL
cgroup_parser-0.0.2.dist-info/top_level.txt
tests/__init__.py
tests/test_main.py
