Metadata-Version: 2.1
Name: cgroup-parser
Version: 0.0.2
Summary: cgroup parser for python
Home-page: https://github.com/ZhuYuJin/cgroup-parser
Author: robertzhu
Author-email: 630268695@qq.com
License: UNKNOWN
Platform: UNKNOWN
Classifier: Programming Language :: Python :: 3
Classifier: License :: OSI Approved :: MIT License
Classifier: Operating System :: OS Independent
Requires-Python: >=3.6
